ttree/__init__.py
ttree/cli.py
tea_tree-0.1.3.dist-info/WHEEL
tea_tree-0.1.3.dist-info/entry_points.txt
tea_tree-0.1.3.dist-info/METADATA
tea_tree-0.1.3.dist-info/RECORD
