Metadata-Version: 2.3
Name: tea-tree
Version: 0.1.3
Summary: A Rich + Typer powered tree viewer that summarizes directories when they get busy.
Requires-Dist: rich>=13.7
Requires-Dist: typer>=0.12
Requires-Dist: pytest>=8.2 ; extra == 'dev'
Requires-Python: >=3.11
Provides-Extra: dev
